Workbook

Sheet Inputs
A1: Lab 3b - Inputs
A2: Blue = given in the lab dataset. Yellow fill = my assumption (edit to run scenarios). Black = formula.
A3: System context (SecureMobile)
A4: Active customers | B4: 500000
A5: Average transaction ($) | B5: 2500
A6: Daily transactions | B6: 50000
A8: Finding | B8: Exploit probability (= ARO) | C8: Loss quantity | D8: Unit loss ($) | E8: SLE basis | F8: ID
A9: API Authentication Bypass | B9: 0.15 | C9: 1 | D9: 5000000 | E9: 1 incident x max single-incident loss | F9: F1
A10: Database Injection | B10: 0.25 | C10: =B4 -> 500000 | D10: 250 | E10: records at risk x cost per record | F10: F2
A11: Session Hijacking | B11: 0.4 | C11: 5000 | D11: 1500 | E11: accounts at risk x avg loss per account | F11: F3
A13: Control | B13: Initial cost ($) | C13: Annual maintenance ($) | D13: Effectiveness | E13: Mitigates (ID)
A14: Advanced API Security Gateway | B14: 350000 | C14: 50000 | D14: 0.9 | E14: F1
A15: Web Application Firewall (WAF) | B15: 150000 | C15: 25000 | D15: 0.75 | E15: F2
A16: Multi-Factor Authentication Enhancement | B16: 200000 | C16: 30000 | D16: 0.95 | E16: F3
A18: Assumptions and thresholds (all mine - not in the lab brief)
A19: Evaluation horizon (years) | B19: 3
A20: Priority 'Critical' if ALE >= | B20: 10000000
A21: Priority 'High' if ALE >= | B21: 1000000
A22: Priority 'Medium' if ALE >= | B22: 250000
A23: Probability band 'High' if >= | B23: 0.35
A24: Probability band 'Medium' if >= | B24: 0.2
A25: Impact band 'High' if SLE >= | B25: 10000000
A26: Impact band 'Medium' if SLE >= | B26: 1000000
A27: Bonus: budget cap on Year-1 outlay ($) | B27: 450000
A29: Heat-map rating matrix (impact down, probability across)
A30: Impact \ Probability | B30: Low | C30: Medium | D30: High
A31: High | B31: Medium | C31: High | D31: High
A32: Medium | B32: Medium | C32: Medium | D32: High
A33: Low | B33: Low | C33: Low | D33: Medium
A36: Notes:
A37: 1. ARO = exploit probability per year (the lab gives probability only; I treat it as one expected exploitation attempt-year).
A38: 2. F1 SLE uses the 'Maximum Single Incident Loss' given. The 48-hour detection time is context only; it is not used in ALE.
A39: 3. F2 SLE assumes all 500,000 records are exposed (worst case) at $250/record.
A40: 4. Each control is mapped to the single finding it addresses: API Gateway->F1, WAF->F2 (injection), MFA->F3 (account takeover).
A41: 5. Effectiveness is applied as a straight % reduction of that finding's ALE.

Sheet Risk
A1: Phase 1 - Risk Exposure (SLE x ARO = ALE)
A4: Vulnerability | B4: SLE ($) | C4: ARO | D4: ALE ($) | E4: % of total ALE | F4: Risk priority | G4: Probability band | H4: Impact band | I4: Heat-map rating | J4: Rank
A5: =Inputs!A9 -> API Authentication Bypass | B5: =Inputs!C9*Inputs!D9 -> 5000000 | C5: =Inputs!B9 -> 0.15 | D5: =B5*C5 -> 750000 | E5: =D5/$D$8 -> 0.021428571 | F5: =IF(D5>=Inputs!$B$20,"Critical",IF(D5>=Inputs!$B$21,"High",IF(D5>=Inputs!$B$22,"Medium","Low"))) -> Medium | G5: =IF(C5>=Inputs!$B$23,"High",IF(C5>=Inputs!$B$24,"Medium","Low")) -> Low | H5: =IF(B5>=Inputs!$B$25,"High",IF(B5>=Inputs!$B$26,"Medium","Low")) -> Medium | I5: =INDEX(Inputs!$B$31:$D$33,MATCH(H5,Inputs!$A$31:$A$33,0),MATCH(G5,Inputs!$B$30:$D$30,0)) -> Medium | J5: =RANK(D5,$D$5:$D$7) -> 3
A6: =Inputs!A10 -> Database Injection | B6: =Inputs!C10*Inputs!D10 -> 125000000 | C6: =Inputs!B10 -> 0.25 | D6: =B6*C6 -> 31250000 | E6: =D6/$D$8 -> 0.89285714 | F6: =IF(D6>=Inputs!$B$20,"Critical",IF(D6>=Inputs!$B$21,"High",IF(D6>=Inputs!$B$22,"Medium","Low"))) -> Critical | G6: =IF(C6>=Inputs!$B$23,"High",IF(C6>=Inputs!$B$24,"Medium","Low")) -> Medium | H6: =IF(B6>=Inputs!$B$25,"High",IF(B6>=Inputs!$B$26,"Medium","Low")) -> High | I6: =INDEX(Inputs!$B$31:$D$33,MATCH(H6,Inputs!$A$31:$A$33,0),MATCH(G6,Inputs!$B$30:$D$30,0)) -> High | J6: =RANK(D6,$D$5:$D$7) -> 1
A7: =Inputs!A11 -> Session Hijacking | B7: =Inputs!C11*Inputs!D11 -> 7500000 | C7: =Inputs!B11 -> 0.4 | D7: =B7*C7 -> 3000000 | E7: =D7/$D$8 -> 0.085714286 | F7: =IF(D7>=Inputs!$B$20,"Critical",IF(D7>=Inputs!$B$21,"High",IF(D7>=Inputs!$B$22,"Medium","Low"))) -> High | G7: =IF(C7>=Inputs!$B$23,"High",IF(C7>=Inputs!$B$24,"Medium","Low")) -> High | H7: =IF(B7>=Inputs!$B$25,"High",IF(B7>=Inputs!$B$26,"Medium","Low")) -> Medium | I7: =INDEX(Inputs!$B$31:$D$33,MATCH(H7,Inputs!$A$31:$A$33,0),MATCH(G7,Inputs!$B$30:$D$30,0)) -> High | J7: =RANK(D7,$D$5:$D$7) -> 2
A8: Total | D8: =SUM(D5:D7) -> 35000000 | E8: =SUM(E5:E7) -> 1

Sheet Controls
A1: Phase 2 - Cost-Benefit Analysis
A2: Year-1 ROI = (annual risk reduction - (initial + annual maintenance)) / (initial + annual maintenance). Payback = initial / (annual risk reduction - annual maintenance).
A4: Control | B4: Initial investment ($) | C4: Annual maintenance ($) | D4: Mitigates | E4: Baseline ALE ($) | F4: Effectiveness | G4: Annual risk reduction ($) | H4: Residual ALE ($) | I4: Year-1 cost ($) | J4: Year-1 ROI | K4: Horizon cost ($) | L4: Horizon benefit ($) | M4: Horizon ROI | N4: Payback (years) | O4: Payback (days)
A5: =Inputs!A14 -> Advanced API Security Gateway | B5: =Inputs!B14 -> 350000 | C5: =Inputs!C14 -> 50000 | D5: =Inputs!E14 -> F1 | E5: =INDEX(Risk!$D$5:$D$7,MATCH(D5,Inputs!$F$9:$F$11,0)) -> 750000 | F5: =Inputs!D14 -> 0.9 | G5: =E5*F5 -> 675000 | H5: =E5-G5 -> 75000 | I5: =B5+C5 -> 400000 | J5: =(G5-I5)/I5 -> 0.6875 | K5: =B5+C5*Inputs!$B$19 -> 500000 | L5: =G5*Inputs!$B$19 -> 2025000 | M5: =(L5-K5)/K5 -> 3.05 | N5: =B5/(G5-C5) -> 0.56 | O5: =N5*365 -> 204.4
A6: =Inputs!A15 -> Web Application Firewall (WAF) | B6: =Inputs!B15 -> 150000 | C6: =Inputs!C15 -> 25000 | D6: =Inputs!E15 -> F2 | E6: =INDEX(Risk!$D$5:$D$7,MATCH(D6,Inputs!$F$9:$F$11,0)) -> 31250000 | F6: =Inputs!D15 -> 0.75 | G6: =E6*F6 -> 23437500 | H6: =E6-G6 -> 7812500 | I6: =B6+C6 -> 175000 | J6: =(G6-I6)/I6 -> 132.92857 | K6: =B6+C6*Inputs!$B$19 -> 225000 | L6: =G6*Inputs!$B$19 -> 70312500 | M6: =(L6-K6)/K6 -> 311.5 | N6: =B6/(G6-C6) -> 0.006406834 | O6: =N6*365 -> 2.3384944
A7: =Inputs!A16 -> Multi-Factor Authentication Enhancement | B7: =Inputs!B16 -> 200000 | C7: =Inputs!C16 -> 30000 | D7: =Inputs!E16 -> F3 | E7: =INDEX(Risk!$D$5:$D$7,MATCH(D7,Inputs!$F$9:$F$11,0)) -> 3000000 | F7: =Inputs!D16 -> 0.95 | G7: =E7*F7 -> 2850000 | H7: =E7-G7 -> 150000 | I7: =B7+C7 -> 230000 | J7: =(G7-I7)/I7 -> 11.391304 | K7: =B7+C7*Inputs!$B$19 -> 290000 | L7: =G7*Inputs!$B$19 -> 8550000 | M7: =(L7-K7)/K7 -> 28.482759 | N7: =B7/(G7-C7) -> 0.070921986 | O7: =N7*365 -> 25.886525
A8: Portfolio (all three) | B8: =SUM(B5:B7) -> 700000 | C8: =SUM(C5:C7) -> 105000 | E8: =SUM(E5:E7) -> 35000000 | G8: =SUM(G5:G7) -> 26962500 | H8: =SUM(H5:H7) -> 8037500 | I8: =SUM(I5:I7) -> 805000 | J8: =(G8-I8)/I8 -> 32.493789 | K8: =SUM(K5:K7) -> 1015000 | L8: =SUM(L5:L7) -> 80887500 | M8: =(L8-K8)/K8 -> 78.692118 | N8: =B8/(G8-C8) -> 0.026063483 | O8: =N8*365 -> 9.5131714

Sheet Summary
A1: Executive Summary - Before vs After Controls
A4: Vulnerability | B4: ALE before ($) | C4: Control | D4: Residual ALE ($) | E4: Risk reduction ($) | F4: Reduction %
A5: =Risk!A5 -> API Authentication Bypass | B5: =Risk!D5 -> 750000 | C5: =Controls!A5 -> Advanced API Security Gateway | D5: =Controls!H5 -> 75000 | E5: =B5-D5 -> 675000 | F5: =E5/B5 -> 0.9
A6: =Risk!A6 -> Database Injection | B6: =Risk!D6 -> 31250000 | C6: =Controls!A6 -> Web Application Firewall (WAF) | D6: =Controls!H6 -> 7812500 | E6: =B6-D6 -> 23437500 | F6: =E6/B6 -> 0.75
A7: =Risk!A7 -> Session Hijacking | B7: =Risk!D7 -> 3000000 | C7: =Controls!A7 -> Multi-Factor Authentication Enhancement | D7: =Controls!H7 -> 150000 | E7: =B7-D7 -> 2850000 | F7: =E7/B7 -> 0.95
A8: Total | B8: =SUM(B5:B7) -> 35000000 | D8: =SUM(D5:D7) -> 8037500 | E8: =SUM(E5:E7) -> 26962500 | F8: =E8/B8 -> 0.77035714
A11: KPI | B11: Value
A12: Total initial investment | B12: =Controls!B8 -> 700000
A13: Annual maintenance | B13: =Controls!C8 -> 105000
A14: Year-1 total cost | B14: =Controls!I8 -> 805000
A15: Annual risk reduction | B15: =Controls!G8 -> 26962500
A16: Portfolio Year-1 ROI | B16: =Controls!J8 -> 32.493789
A17: Portfolio payback (days) | B17: =Controls!O8 -> 9.5131714
A18: Residual ALE after all controls | B18: =D8 -> 8037500

Sheet Projection
A1: Risk reduction over time
A3: Cumulative net benefit by year ($) = -initial + (annual risk reduction - annual maintenance) x year
A4: Control | B4: Year 0 | C4: Year 1 | D4: Year 2 | E4: Year 3 | F4: Year 4 | G4: Year 5
A5: Year index | B5: 0 | C5: 1 | D5: 2 | E5: 3 | F5: 4 | G5: 5
A6: =Controls!A5 -> Advanced API Security Gateway | B6: =-Controls!$B$5+(Controls!$G$5-Controls!$C$5)*B$5 -> -350000 | C6: =-Controls!$B$5+(Controls!$G$5-Controls!$C$5)*C$5 -> 275000 | D6: =-Controls!$B$5+(Controls!$G$5-Controls!$C$5)*D$5 -> 900000 | E6: =-Controls!$B$5+(Controls!$G$5-Controls!$C$5)*E$5 -> 1525000 | F6: =-Controls!$B$5+(Controls!$G$5-Controls!$C$5)*F$5 -> 2150000 | G6: =-Controls!$B$5+(Controls!$G$5-Controls!$C$5)*G$5 -> 2775000
A7: =Controls!A6 -> Web Application Firewall (WAF) | B7: =-Controls!$B$6+(Controls!$G$6-Controls!$C$6)*B$5 -> -150000 | C7: =-Controls!$B$6+(Controls!$G$6-Controls!$C$6)*C$5 -> 23262500 | D7: =-Controls!$B$6+(Controls!$G$6-Controls!$C$6)*D$5 -> 46675000 | E7: =-Controls!$B$6+(Controls!$G$6-Controls!$C$6)*E$5 -> 70087500 | F7: =-Controls!$B$6+(Controls!$G$6-Controls!$C$6)*F$5 -> 93500000 | G7: =-Controls!$B$6+(Controls!$G$6-Controls!$C$6)*G$5 -> 116912500
A8: =Controls!A7 -> Multi-Factor Authentication Enhancement | B8: =-Controls!$B$7+(Controls!$G$7-Controls!$C$7)*B$5 -> -200000 | C8: =-Controls!$B$7+(Controls!$G$7-Controls!$C$7)*C$5 -> 2620000 | D8: =-Controls!$B$7+(Controls!$G$7-Controls!$C$7)*D$5 -> 5440000 | E8: =-Controls!$B$7+(Controls!$G$7-Controls!$C$7)*E$5 -> 8260000 | F8: =-Controls!$B$7+(Controls!$G$7-Controls!$C$7)*F$5 -> 11080000 | G8: =-Controls!$B$7+(Controls!$G$7-Controls!$C$7)*G$5 -> 13900000
A9: Portfolio | B9: =SUM(B6:B8) -> -700000 | C9: =SUM(C6:C8) -> 26157500 | D9: =SUM(D6:D8) -> 53015000 | E9: =SUM(E6:E8) -> 79872500 | F9: =SUM(F6:F8) -> 106730000 | G9: =SUM(G6:G8) -> 133587500
A12: Phased roll-out: go-live month per control (assumption)
A13: Control | B13: Go-live month
A14: =Controls!A5 -> Advanced API Security Gateway | B14: 6
A15: =Controls!A6 -> Web Application Firewall (WAF) | B15: 1
A16: =Controls!A7 -> Multi-Factor Authentication Enhancement | B16: 3
A18: Month | B18: Annualised residual exposure ($)
A19: 0 | B19: =Risk!$D$8-SUMPRODUCT((A19>=$B$14:$B$16)*Controls!$G$5:$G$7) -> 35000000
A20: 1 | B20: =Risk!$D$8-SUMPRODUCT((A20>=$B$14:$B$16)*Controls!$G$5:$G$7) -> 11562500
A21: 2 | B21: =Risk!$D$8-SUMPRODUCT((A21>=$B$14:$B$16)*Controls!$G$5:$G$7) -> 11562500
A22: 3 | B22: =Risk!$D$8-SUMPRODUCT((A22>=$B$14:$B$16)*Controls!$G$5:$G$7) -> 8712500
A23: 4 | B23: =Risk!$D$8-SUMPRODUCT((A23>=$B$14:$B$16)*Controls!$G$5:$G$7) -> 8712500
A24: 5 | B24: =Risk!$D$8-SUMPRODUCT((A24>=$B$14:$B$16)*Controls!$G$5:$G$7) -> 8712500
A25: 6 | B25: =Risk!$D$8-SUMPRODUCT((A25>=$B$14:$B$16)*Controls!$G$5:$G$7) -> 8037500
A26: 7 | B26: =Risk!$D$8-SUMPRODUCT((A26>=$B$14:$B$16)*Controls!$G$5:$G$7) -> 8037500
A27: 8 | B27: =Risk!$D$8-SUMPRODUCT((A27>=$B$14:$B$16)*Controls!$G$5:$G$7) -> 8037500
A28: 9 | B28: =Risk!$D$8-SUMPRODUCT((A28>=$B$14:$B$16)*Controls!$G$5:$G$7) -> 8037500
A29: 10 | B29: =Risk!$D$8-SUMPRODUCT((A29>=$B$14:$B$16)*Controls!$G$5:$G$7) -> 8037500
A30: 11 | B30: =Risk!$D$8-SUMPRODUCT((A30>=$B$14:$B$16)*Controls!$G$5:$G$7) -> 8037500
A31: 12 | B31: =Risk!$D$8-SUMPRODUCT((A31>=$B$14:$B$16)*Controls!$G$5:$G$7) -> 8037500

Sheet Bonus_Budget
A1: Bonus - optimal control selection under a budget
A3: Budget cap on Year-1 outlay ($) | B3: =Inputs!B27 -> 450000
A5: Combination | B5: API GW | C5: WAF | D5: MFA | E5: Initial ($) | F5: Year-1 outlay ($) | G5: Annual risk reduction ($) | H5: Year-1 net benefit ($) | I5: Within budget? | J5: Eligible net benefit ($)
A6: None | B6: 0 | C6: 0 | D6: 0 | E6: =B6*Controls!$B$5+C6*Controls!$B$6+D6*Controls!$B$7 -> 0 | F6: =B6*Controls!$I$5+C6*Controls!$I$6+D6*Controls!$I$7 -> 0 | G6: =B6*Controls!$G$5+C6*Controls!$G$6+D6*Controls!$G$7 -> 0 | H6: =G6-F6 -> 0 | I6: =IF(F6<=$B$3,"Yes","No") -> Yes | J6: =IF(I6="Yes",H6,"") -> 0
A7: API GW | B7: 1 | C7: 0 | D7: 0 | E7: =B7*Controls!$B$5+C7*Controls!$B$6+D7*Controls!$B$7 -> 350000 | F7: =B7*Controls!$I$5+C7*Controls!$I$6+D7*Controls!$I$7 -> 400000 | G7: =B7*Controls!$G$5+C7*Controls!$G$6+D7*Controls!$G$7 -> 675000 | H7: =G7-F7 -> 275000 | I7: =IF(F7<=$B$3,"Yes","No") -> Yes | J7: =IF(I7="Yes",H7,"") -> 275000
A8: WAF | B8: 0 | C8: 1 | D8: 0 | E8: =B8*Controls!$B$5+C8*Controls!$B$6+D8*Controls!$B$7 -> 150000 | F8: =B8*Controls!$I$5+C8*Controls!$I$6+D8*Controls!$I$7 -> 175000 | G8: =B8*Controls!$G$5+C8*Controls!$G$6+D8*Controls!$G$7 -> 23437500 | H8: =G8-F8 -> 23262500 | I8: =IF(F8<=$B$3,"Yes","No") -> Yes | J8: =IF(I8="Yes",H8,"") -> 23262500
A9: MFA | B9: 0 | C9: 0 | D9: 1 | E9: =B9*Controls!$B$5+C9*Controls!$B$6+D9*Controls!$B$7 -> 200000 | F9: =B9*Controls!$I$5+C9*Controls!$I$6+D9*Controls!$I$7 -> 230000 | G9: =B9*Controls!$G$5+C9*Controls!$G$6+D9*Controls!$G$7 -> 2850000 | H9: =G9-F9 -> 2620000 | I9: =IF(F9<=$B$3,"Yes","No") -> Yes | J9: =IF(I9="Yes",H9,"") -> 2620000
A10: API GW + WAF | B10: 1 | C10: 1 | D10: 0 | E10: =B10*Controls!$B$5+C10*Controls!$B$6+D10*Controls!$B$7 -> 500000 | F10: =B10*Controls!$I$5+C10*Controls!$I$6+D10*Controls!$I$7 -> 575000 | G10: =B10*Controls!$G$5+C10*Controls!$G$6+D10*Controls!$G$7 -> 24112500 | H10: =G10-F10 -> 23537500 | I10: =IF(F10<=$B$3,"Yes","No") -> No | J10: =IF(I10="Yes",H10,"")
A11: API GW + MFA | B11: 1 | C11: 0 | D11: 1 | E11: =B11*Controls!$B$5+C11*Controls!$B$6+D11*Controls!$B$7 -> 550000 | F11: =B11*Controls!$I$5+C11*Controls!$I$6+D11*Controls!$I$7 -> 630000 | G11: =B11*Controls!$G$5+C11*Controls!$G$6+D11*Controls!$G$7 -> 3525000 | H11: =G11-F11 -> 2895000 | I11: =IF(F11<=$B$3,"Yes","No") -> No | J11: =IF(I11="Yes",H11,"")
A12: WAF + MFA | B12: 0 | C12: 1 | D12: 1 | E12: =B12*Controls!$B$5+C12*Controls!$B$6+D12*Controls!$B$7 -> 350000 | F12: =B12*Controls!$I$5+C12*Controls!$I$6+D12*Controls!$I$7 -> 405000 | G12: =B12*Controls!$G$5+C12*Controls!$G$6+D12*Controls!$G$7 -> 26287500 | H12: =G12-F12 -> 25882500 | I12: =IF(F12<=$B$3,"Yes","No") -> Yes | J12: =IF(I12="Yes",H12,"") -> 25882500
A13: All three | B13: 1 | C13: 1 | D13: 1 | E13: =B13*Controls!$B$5+C13*Controls!$B$6+D13*Controls!$B$7 -> 700000 | F13: =B13*Controls!$I$5+C13*Controls!$I$6+D13*Controls!$I$7 -> 805000 | G13: =B13*Controls!$G$5+C13*Controls!$G$6+D13*Controls!$G$7 -> 26962500 | H13: =G13-F13 -> 26157500 | I13: =IF(F13<=$B$3,"Yes","No") -> No | J13: =IF(I13="Yes",H13,"")
A16: Best affordable combination | B16: =INDEX(A6:A13,MATCH(MAX(J6:J13),J6:J13,0)) -> WAF + MFA
A17: Its Year-1 net benefit ($) | B17: =MAX(J6:J13) -> 25882500
